ChangeLog
LICENSE
MANIFEST.in
README.md
requirements.txt
setup.cfg
setup.py
syseleven/__init__.py
syseleven.cloudutils.egg-info/PKG-INFO
syseleven.cloudutils.egg-info/SOURCES.txt
syseleven.cloudutils.egg-info/dependency_links.txt
syseleven.cloudutils.egg-info/entry_points.txt
syseleven.cloudutils.egg-info/namespace_packages.txt
syseleven.cloudutils.egg-info/not-zip-safe
syseleven.cloudutils.egg-info/pbr.json
syseleven.cloudutils.egg-info/requires.txt
syseleven.cloudutils.egg-info/top_level.txt
syseleven/cloudutils/__init__.py
syseleven/cloudutils/scloud/__init__.py
syseleven/cloudutils/scloud/opts.py
syseleven/cloudutils/scloud/shell.py
syseleven/cloudutils/show_heat_floating_ips/__init__.py
syseleven/cloudutils/show_heat_floating_ips/opts.py
syseleven/cloudutils/show_heat_floating_ips/shell.py